CHANGES.rst
MANIFEST.in
README.rst
setup.py
bushy/__init__.py
bushy/_pivotal.py
bushy/base.py
bushy/scripts.py
bushy.egg-info/PKG-INFO
bushy.egg-info/SOURCES.txt
bushy.egg-info/dependency_links.txt
bushy.egg-info/entry_points.txt
bushy.egg-info/requires.txt
bushy.egg-info/top_level.txt