Metadata-Version: 1.0
Name: bushy
Version: 0.2.5
Summary: A git workflow plugin.
Home-page: https://github.com/junkafarian/bushy
Author: junkafarian
Author-email: junkafarian@gmail.com
License: UNKNOWN
Platform: UNKNOWN
Classifier: Development Status :: 3 - Alpha
Classifier: Programming Language :: Python
Classifier: Intended Audience :: Developers
Classifier: Natural Language :: English
Classifier: Topic :: Software Development
Classifier: Topic :: Internet :: WWW/HTTP
Classifier: Topic :: Software Development :: Bug Tracking
Classifier: Topic :: Utilities
Classifier: Environment :: Console
